mcerp3/__init__.py
mcerp3/correlate.py
mcerp3/lhd.py
mcerp3/stats.py
mcerp3/umath.py
mcerp3-1.0.3.dist-info/METADATA
mcerp3-1.0.3.dist-info/RECORD
mcerp3-1.0.3.dist-info/WHEEL
mcerp3-1.0.3.dist-info/top_level.txt
